{
    "data": [
        {
            "id": "47fe850b0d821eaa5228d882f67001fc",
            "name": "Realidad emocional del parto",
            "description": "La preparación para el parto implica una preparación física, mental y emocional. Aprenda la importancia de crear sistemas de apoyo sólidos, comprender las perspectivas culturales y planificar la recuperación posparto para garantizar una experiencia segura y apoyada.",
            "language": "es",
            "thumbnail": "assets/Emotional Realities of Child Labor.png",
            "html": "<h4>Realidad emocional del parto</h4><p>El parto es un acontecimiento importante en la vida de muchas personas, y prepararse para él puede ayudarlas a sentirse más seguras y respaldadas. He aquí unos consejos para afrontar este viaje.</p><p><strong>Preparación física</strong></p><p>Mantener la salud física durante el embarazo puede ser beneficioso. Practicar actividades como caminar, nadar o yoga prenatal puede ayudar a fortalecer los músculos, mejorar la flexibilidad y reducir las molestias. Es aconsejable consultar con un profesional sanitario antes de iniciar cualquier nueva rutina de ejercicios para asegurarse de que es adecuada para las circunstancias individuales.</p><p>Una dieta equilibrada rica en frutas, verduras, proteínas magras y cereales integrales puede contribuir al bienestar general. Mantenerse hidratadas también es importante, ya que favorece la digestión y la circulación.</p><p><strong>Preparación mental y emocional</strong></p><p>La preparación mental es igualmente importante. Técnicas como la respiración profunda, la meditación y la atención plena pueden ayudar a controlar el estrés y la ansiedad. Estas prácticas pueden promover una sensación de calma y concentración, que algunas personas encuentran útil durante el parto.</p><p>Ponerse en contacto con otras personas que hayan vivido la experiencia del parto puede aportar valiosas ideas y apoyo. Compartir experiencias y debatir las expectativas puede ayudar a las personas a sentirse más informadas y menos aprensivas.</p><p><strong>Sistemas de apoyo</strong></p><p>Contar con un sistema de apoyo puede marcar la diferencia. Una compañera de parto, una doula o una comadrona pueden ofrecer apoyo emocional y ayudar con medidas de confort durante el parto. Es conveniente comunicar las preferencias y expectativas al equipo de apoyo con antelación.</p><p><strong>Perspectivas culturales</strong></p><p>Cada lugar tiene su propia forma de abordar el parto. Por ejemplo, en Etiopía, las comadronas desempeñan un papel crucial a la hora de ofrecer un apoyo respetuoso y de alta calidad en el parto, lo que a menudo se traduce en menos intervenciones y estancias hospitalarias más cortas. Explorar las prácticas y opciones locales puede ayudar a las muejeres a tomar decisiones informadas que se ajusten a sus valores y preferencias.</p><p><strong>Consideraciones sobre el posparto</strong></p><p>Después del parto, es importante centrarse en la recuperación y el autocuidado. Descansar, alimentarse adecuadamente y buscar ayuda cuando sea necesario son decisiones que pueden contribuir a la curación y a la adaptación a las nuevas rutinas. Preparar el entorno doméstico y organizar el apoyo durante las primeras semanas también puede facilitar la transición.</p><p>Si se tienen en cuenta estos aspectos, las mujeres pueden afrontar el parto con una sensación de preparación y confianza. Recuerda que la experiencia de cada persona es única y que buscar orientación de profesionales sanitarios y redes de apoyo puede proporcionar asistencia personalizada.</p><p><strong>Referencias</strong></p><p>Advantia Health. (s.f.). Preparación para el parto natural: Consejos de una enfermera con experiencia en partos. Extraído de [https://www.advantiahealth.com/womens-health-blog/preparing-for-natural-childbirth-tips-from-an-experienced-labor-and-delivery-nurse/](https://www.advantiahealth.com/womens-health-blog/preparing-for-natural-childbirth-tips-from-an-experienced-labor-and-delivery-nurse/)</p><p>Mima Reino Unido. (s.f.). Preparación para el parto: consejos y sugerencias para el parto. Extraído de <https://www.pampers.co.uk/pregnancy/giving-birth/article/labour-tips></p><p>Time. (2016, 5 de mayo). Las matronas son esenciales para la salud mundial. Extraído de [https://time.com/4318462/international-day-of-the-midwife/](https://time.com/4318462/international-day-of-the-midwife/)</p><p>WebMD. (s.f.). Preparárate para recibir a tu bebé: Consejos para un cambio suave. Extraído de [https://www.webmd.com/baby/tips-to-prepare-for-baby](https://www.webmd.com/baby/tips-to-prepare-for-baby)</p><p>*Este contenido tiene únicamente fines de información general. No pretende ser fiable y no sustituye al asesoramiento financiero profesional basado en sus condiciones y circunstancias individuales. El uso de los servicios de Caravan está sujeto a términos y condiciones adicionales.*</p>",
            "content": "**Realidad emocional del parto** El parto es un acontecimiento importante en la vida de muchas personas, y prepararse para él puede ayudarlas a sentirse más seguras y respaldadas. He aquí unos consejos para afrontar este viaje. **Preparación física** Mantener la salud física durante el embarazo puede ser beneficioso. Practicar actividades como caminar, nadar o yoga prenatal puede ayudar a fortalecer los músculos, mejorar la flexibilidad y reducir las molestias. Es aconsejable consultar con un profesional sanitario antes de iniciar cualquier nueva rutina de ejercicios para asegurarse de que es adecuada para las circunstancias individuales. Una dieta equilibrada rica en frutas, verduras, proteínas magras y cereales integrales puede contribuir al bienestar general. Mantenerse hidratadas también es importante, ya que favorece la digestión y la circulación. **Preparación mental y emocional** La preparación mental es igualmente importante. Técnicas como la respiración profunda, la meditación y la atención plena pueden ayudar a controlar el estrés y la ansiedad. Estas prácticas pueden promover una sensación de calma y concentración, que algunas personas encuentran útil durante el parto. Ponerse en contacto con otras personas que hayan vivido la experiencia del parto puede aportar valiosas ideas y apoyo. Compartir experiencias y debatir las expectativas puede ayudar a las personas a sentirse más informadas y menos aprensivas. **Sistemas de apoyo** Contar con un sistema de apoyo puede marcar la diferencia. Una compañera de parto, una doula o una comadrona pueden ofrecer apoyo emocional y ayudar con medidas de confort durante el parto. Es conveniente comunicar las preferencias y expectativas al equipo de apoyo con antelación. **Perspectivas culturales** Cada lugar tiene su propia forma de abordar el parto. Por ejemplo, en Etiopía, las comadronas desempeñan un papel crucial a la hora de ofrecer un apoyo respetuoso y de alta calidad en el parto, lo que a menudo se traduce en menos intervenciones y estancias hospitalarias más cortas. Explorar las prácticas y opciones locales puede ayudar a las muejeres a tomar decisiones informadas que se ajusten a sus valores y preferencias. **Consideraciones sobre el posparto** Después del parto, es importante centrarse en la recuperación y el autocuidado. Descansar, alimentarse adecuadamente y buscar ayuda cuando sea necesario son decisiones que pueden contribuir a la curación y a la adaptación a las nuevas rutinas. Preparar el entorno doméstico y organizar el apoyo durante las primeras semanas también puede facilitar la transición. Si se tienen en cuenta estos aspectos, las mujeres pueden afrontar el parto con una sensación de preparación y confianza. Recuerda que la experiencia de cada persona es única y que buscar orientación de profesionales sanitarios y redes de apoyo puede proporcionar asistencia personalizada. **Referencias** Advantia Health. (s.f.). Preparación para el parto natural: Consejos de una enfermera con experiencia en partos. Extraído de [https://www.advantiahealth.com/womens-health-blog/preparing-for-natural-childbirth-tips-from-an-experienced-labor-and-delivery-nurse/](https://www.advantiahealth.com/womens-health-blog/preparing-for-natural-childbirth-tips-from-an-experienced-labor-and-delivery-nurse/) Mima Reino Unido. (s.f.). Preparación para el parto: consejos y sugerencias para el parto. Extraído de <https://www.pampers.co.uk/pregnancy/giving-birth/article/labour-tips> Time. (2016, 5 de mayo). Las matronas son esenciales para la salud mundial. Extraído de [https://time.com/4318462/international-day-of-the-midwife/](https://time.com/4318462/international-day-of-the-midwife/) WebMD. (s.f.). Preparárate para recibir a tu bebé: Consejos para un cambio suave. Extraído de [https://www.webmd.com/baby/tips-to-prepare-for-baby](https://www.webmd.com/baby/tips-to-prepare-for-baby) *Este contenido tiene únicamente fines de información general. No pretende ser fiable y no sustituye al asesoramiento financiero profesional basado en sus condiciones y circunstancias individuales. El uso de los servicios de Caravan está sujeto a términos y condiciones adicionales.*"
        }
    ],
    "status": 200
}