{
    "data": [
        {
            "id": "9929565057a437edae0aa6a0e72c9cac",
            "name": "Comprender los distintos estilos de comunicación",
            "description": "Comprender y adaptarse a estilos de comunicación variados para mejorar el trabajo en equipo y la inclusión.",
            "language": "es",
            "thumbnail": "assets/Understanding Different Communication Styles.png",
            "html": "<h4>Comprender los distintos estilos de comunicación</h4><p>Comunicarse bien es la base de unas relaciones sanas y de un buen trabajo en equipo. Pero no todo el mundo se comunica igual: la forma en que lo haces depende de tu personalidad, tus preferencias y tus prioridades. Entender estos diferentes estilos puede ayudarte a crear espacios más inclusivos, mejorar la colaboración y hacer que todo el mundo se sientan escuchados. Estas son tres claves que conviene tener en cuenta sobre los estilos de comunicación:</p><p><strong>Comunicación introvertida frente a comunicación extrovertida</strong></p><p>Los comunicadores introvertidos tienden a preferir las conversaciones meditadas y reflexivas. Es posible que necesiten tiempo para procesar sus pensamientos antes de hablar y, a menudo, se desenvuelven mejor en conversaciones individuales o en grupos reducidos. Los introvertidos valoran más el diálogo significativo que la charla superficial, lo que les convierte en excelentes oyentes.</p><p>Por otra parte, a los comunicadores extrovertidos les estimula la interacción. Suelen pensar en voz alta, disfrutan con los intercambios dinámicos y se sienten más cómodos en debates de grupos grandes. Los extrovertidos pueden dominar las conversaciones, pero también son expertos en establecer contactos a través de su compromiso entusiasta.</p><p>Equilibrar estos estilos implica reconocer cuándo proporcionar un espacio para la reflexión y cuándo fomentar el diálogo abierto, asegurando que todos tengan la oportunidad de contribuir.</p><p><strong>Comunicación rápida frente a comunicación lenta</strong></p><p>Los comunicadores rápidos prefieren ir al grano rápidamente y prosperan en entornos en los que las decisiones y las ideas se mueven con rapidez. Sobresalen en las lluvias de ideas y la resolución de problemas, pero pueden precipitar sin querer a otras personas que necesitan más tiempo para considerar sus respuestas.</p><p>Los comunicadores lentos adoptan un enfoque más comedido. Valoran la minuciosidad, prefieren sopesar las opciones cuidadosamente y suelen aportar calma a las discusiones. Aunque su ritmo pausado puede parecer cauteloso, garantiza que las decisiones estén bien meditadas y sean equilibradas.</p><p>Para conciliar estos estilos, practicar la paciencia y adaptar el ritmo al contexto de la conversación puede ayudar a garantizar que se respeten todas las perspectivas.</p><p><strong>Comunicación relacional vs. comunicación centrada en tareas</strong></p><p>Los comunicadores relacionales dan prioridad al establecimiento de vínculos y al fomento de la armonía. Se centran en comprender las emociones, mantener relaciones positivas y asegurarse de que la colaboración sea inclusiva y solidaria. En ocasiones, los comunicadores relacionales pueden restar importancia a la urgencia para preservar la cohesión del grupo.</p><p>En cambio, los comunicadores centrados en tareas se centran en alcanzar objetivos y completar tareas eficientemente. Enfatizan la estructura, los plazos y los resultados, lo que a veces puede parecer impersonal o demasiado directo.</p><p>Equilibrar estos estilos exige reconocer la importancia tanto de la dinámica interpersonal como de la productividad. Un enfoque relacional ayuda a mantener la moral, mientras que la concentración en las tareas garantiza el cumplimiento de los objetivos.</p><p>Reconocer y apreciar los diferentes estilos de comunicación es fundamental para establecer relaciones más sólidas y alcanzar el éxito en el ámbito personal y profesional. Si comprendemos nuestras preferencias, ya sean introvertidas o extrovertidas, rápidas o lentas, relacionales o centradas en las tareas, podremos adaptar nuestros enfoques para promover una comunicación más clara e integradora.</p><p><strong>Referencias</strong></p><ul><li>Goleman, D. (1995). <em>Inteligencia emocional: por qué puede importar más que el coeficiente intelectual</em>.</li><li>Caín, S. (2012). <em>Quiet: El poder de los introvertidos en un mundo que no puede dejar de hablar</em>.</li><li>Robbins, S. P., & Judge, T. A. (2019). <em>Comportamiento Organizacional</em>.</li></ul><p>*\\\\*\\\\*Solo con fines informativos. Consulta siempre a un profesional de la salud, financiero, de inversiones, fiscal o legal, ya que este artículo no es un recurso completo sobre estos temas, no se debe confiar en él y no debe considerarse asesoramiento médico, financiero o legal.**</p>",
            "content": "**Comprender los distintos estilos de comunicación** Comunicarse bien es la base de unas relaciones sanas y de un buen trabajo en equipo. Pero no todo el mundo se comunica igual: la forma en que lo haces depende de tu personalidad, tus preferencias y tus prioridades. Entender estos diferentes estilos puede ayudarte a crear espacios más inclusivos, mejorar la colaboración y hacer que todo el mundo se sientan escuchados. Estas son tres claves que conviene tener en cuenta sobre los estilos de comunicación: **Comunicación introvertida frente a comunicación extrovertida** Los comunicadores introvertidos tienden a preferir las conversaciones meditadas y reflexivas. Es posible que necesiten tiempo para procesar sus pensamientos antes de hablar y, a menudo, se desenvuelven mejor en conversaciones individuales o en grupos reducidos. Los introvertidos valoran más el diálogo significativo que la charla superficial, lo que les convierte en excelentes oyentes. Por otra parte, a los comunicadores extrovertidos les estimula la interacción. Suelen pensar en voz alta, disfrutan con los intercambios dinámicos y se sienten más cómodos en debates de grupos grandes. Los extrovertidos pueden dominar las conversaciones, pero también son expertos en establecer contactos a través de su compromiso entusiasta. Equilibrar estos estilos implica reconocer cuándo proporcionar un espacio para la reflexión y cuándo fomentar el diálogo abierto, asegurando que todos tengan la oportunidad de contribuir. **Comunicación rápida frente a comunicación lenta** Los comunicadores rápidos prefieren ir al grano rápidamente y prosperan en entornos en los que las decisiones y las ideas se mueven con rapidez. Sobresalen en las lluvias de ideas y la resolución de problemas, pero pueden precipitar sin querer a otras personas que necesitan más tiempo para considerar sus respuestas. Los comunicadores lentos adoptan un enfoque más comedido. Valoran la minuciosidad, prefieren sopesar las opciones cuidadosamente y suelen aportar calma a las discusiones. Aunque su ritmo pausado puede parecer cauteloso, garantiza que las decisiones estén bien meditadas y sean equilibradas. Para conciliar estos estilos, practicar la paciencia y adaptar el ritmo al contexto de la conversación puede ayudar a garantizar que se respeten todas las perspectivas. **Comunicación relacional vs. comunicación centrada en tareas** Los comunicadores relacionales dan prioridad al establecimiento de vínculos y al fomento de la armonía. Se centran en comprender las emociones, mantener relaciones positivas y asegurarse de que la colaboración sea inclusiva y solidaria. En ocasiones, los comunicadores relacionales pueden restar importancia a la urgencia para preservar la cohesión del grupo. En cambio, los comunicadores centrados en tareas se centran en alcanzar objetivos y completar tareas eficientemente. Enfatizan la estructura, los plazos y los resultados, lo que a veces puede parecer impersonal o demasiado directo. Equilibrar estos estilos exige reconocer la importancia tanto de la dinámica interpersonal como de la productividad. Un enfoque relacional ayuda a mantener la moral, mientras que la concentración en las tareas garantiza el cumplimiento de los objetivos. Reconocer y apreciar los diferentes estilos de comunicación es fundamental para establecer relaciones más sólidas y alcanzar el éxito en el ámbito personal y profesional. Si comprendemos nuestras preferencias, ya sean introvertidas o extrovertidas, rápidas o lentas, relacionales o centradas en las tareas, podremos adaptar nuestros enfoques para promover una comunicación más clara e integradora. **Referencias** * Goleman, D. (1995). *Inteligencia emocional: por qué puede importar más que el coeficiente intelectual*. * Caín, S. (2012). *Quiet: El poder de los introvertidos en un mundo que no puede dejar de hablar*. * Robbins, S. P., & Judge, T. A. (2019). *Comportamiento Organizacional*. **Solo con fines informativos. Consulta siempre a un profesional de la salud, financiero, de inversiones, fiscal o legal, ya que este artículo no es un recurso completo sobre estos temas, no se debe confiar en él y no debe considerarse asesoramiento médico, financiero o legal.**"
        }
    ],
    "status": 200
}